pyconverters_cairn_xml/__init__.py
pyconverters_cairn_xml/cairn_xml.py
pyconverters_cairn_xml-0.5.86.dist-info/entry_points.txt
pyconverters_cairn_xml-0.5.86.dist-info/licenses/LICENSE
pyconverters_cairn_xml-0.5.86.dist-info/WHEEL
pyconverters_cairn_xml-0.5.86.dist-info/METADATA
pyconverters_cairn_xml-0.5.86.dist-info/RECORD
